Metadata-Version: 2.4
Name: aegisx.ext.google
Version: 0.1.0
Summary: Google Cloud integrations for AegisX
Home-page: https://github.com/tensorshield/python-aegisx
Author: Immortal Izzy
Author-email: immortal.izzy@tensorshield.ai
Classifier: Development Status :: 4 - Beta
Classifier: Environment :: Web Environment
Classifier: Framework :: Pydantic :: 2
Classifier: Intended Audience :: Developers
Classifier: License :: OSI Approved :: MIT License
Classifier: Operating System :: MacOS
Classifier: Operating System :: POSIX
Classifier: Operating System :: POSIX :: Linux
Classifier: Programming Language :: Python :: 3.13
Classifier: Programming Language :: Python :: 3.14
Classifier: Programming Language :: Python :: 3 :: Only
Classifier: Topic :: Communications
Classifier: Topic :: Internet :: WWW/HTTP
Classifier: Topic :: Office/Business :: Financial
Classifier: Topic :: Security
Classifier: Topic :: Software Development :: Libraries
Requires-Dist: aegisx.ext.jose>=0.1.0
Requires-Dist: aegisx.ext.oauth>=0.0.4
Requires-Dist: fastapi
Requires-Dist: httpx
Requires-Dist: google-auth
Requires-Dist: google-auth-oauthlib
Requires-Dist: google-auth-httplib2
Requires-Dist: google-cloud-iam
Provides-Extra: develop
Requires-Dist: aegisx.ext.iam; extra == "develop"
Requires-Dist: pytest; extra == "develop"
Requires-Dist: pytest_asyncio; extra == "develop"
Requires-Dist: coverage; extra == "develop"
Dynamic: author
Dynamic: author-email
Dynamic: classifier
Dynamic: home-page
Dynamic: provides-extra
Dynamic: requires-dist
Dynamic: summary
